collapser.py
html2nb.py
splitmerge.py
tm351_nb_utils.py
updaters.py
ou_nb_workflow_tools/__init__.py
ou_nb_workflow_tools/blank_cell_cleaner.py
ou_nb_workflow_tools/cell_run_status_checker.py
ou_nb_workflow_tools/check_cells_tagged.py
ou_nb_workflow_tools/cli.py
ou_nb_workflow_tools/cnb2jl_ext_migrate.py
ou_nb_workflow_tools/code_cell_output_cleaner.py
ou_nb_workflow_tools/figure_cell_autotagger.py
ou_nb_workflow_tools/html2myst_converter.py
ou_nb_workflow_tools/imagetable.py
ou_nb_workflow_tools/metadata_cleaner.py
ou_nb_workflow_tools/section_splitter.py
ou_nb_workflow_tools/separator_fixer.py
ou_nb_workflow_tools/tagged_cell_remover.py
ou_nb_workflow_tools/tags_collapser.py
ou_nb_workflow_tools/utils.py
ou_nb_workflow_tools/warning_spotter.py
tm351_nb_utils-0.0.36.dist-info/LICENSE
tm351_nb_utils-0.0.36.dist-info/METADATA
tm351_nb_utils-0.0.36.dist-info/WHEEL
tm351_nb_utils-0.0.36.dist-info/entry_points.txt
tm351_nb_utils-0.0.36.dist-info/top_level.txt
tm351_nb_utils-0.0.36.dist-info/RECORD
