Metadata-Version: 2.1
Name: tm351-nb-utils
Version: 0.0.36
Home-page: https://github.com/innovationOUtside/nb_workflow_tools/
Author: Tony Hirst
Author-email: tony.hirst@gmail.com
License-File: LICENSE
Requires-Dist: Click
Requires-Dist: tabulate
Requires-Dist: pytest
Requires-Dist: nbval
Requires-Dist: PyGithub
Requires-Dist: beautifulsoup4
Requires-Dist: humanize
